vm.v
module vm(escolher,inserir_dinheiro,dar_troco,
produto_escolhido, dinheiro_inserido, produto_vendido,
carteira,valor_troco,dinheiro_inserido_c, dinheiro_inserido_d,
dinheiro_inserido_u, reset_n,clock, moedas_inseridas,moedas_carteira);

	input[1:0] escolher, inserir_dinheiro, dar_troco;
	input[7:0] produto_escolhido, dinheiro_inserido;
	input reset_n;
	input clock;
	output reg[7:0] produto_vendido, carteira, valor_troco;
	output reg[3:0]	dinheiro_inserido_c, dinheiro_inserido_d, dinheiro_inserido_u;
	
	input[23:0] moedas_inseridas;
	output reg[23:0] moedas_carteira;
	//moedas[7:0] = moedas de R$0,25
	//moedas[15:8] = moedas de R$0,50
	//moedas[23:16] = moedas de R$1,00
	
	reg[1:0] estado_atual;
	reg[7:0] price;
	reg[11:0] cdu;
	reg[7:0] moedas_25,moedas_50,moedas_100;
	reg[23:0] moedas_troco;
	reg[1:0] flag_sem_troco_devolver_dinheiro_inserido;
	reg[1:0] flag_dinheiro_insuficiente;
	
	reg[1:0] executou_start, executou_insert_money, executou_give_change;
	
	parameter espera=0,start=1,insert_money=2,give_change=3;
	
	//parte combinacional
	always @(posedge clock, negedge reset_n)
		if(~reset_n) begin
			flag_dinheiro_insuficiente = 0;
			flag_sem_troco_devolver_dinheiro_inserido = 0;
			price = 0;
			carteira = 0;
			valor_troco = 0;
			dinheiro_inserido_c = 0;
			dinheiro_inserido_d = 0;
			dinheiro_inserido_u = 0;
			produto_vendido = 0;
			cdu=0;
			moedas_carteira = 0;
			moedas_troco = 0;
			executou_start = 0;
			executou_insert_money = 0;
			executou_give_change = 0;
		end
		else
		case(estado_atual)
			espera:begin
				//carteira não é zerada
				flag_dinheiro_insuficiente = 0;
				flag_sem_troco_devolver_dinheiro_inserido = 0;
				price = 0;
				valor_troco = 0;
				dinheiro_inserido_c = 0;
				dinheiro_inserido_d = 0;
				dinheiro_inserido_u = 0;
				produto_vendido = 0;
				moedas_troco = 0;
				cdu=0;	
				executou_start = 0;
				executou_insert_money = 0;
				executou_give_change = 0;				
			end
			start:begin
				if(!executou_start) begin
					case(produto_escolhido)
						1: begin
							price = 50;
						end
						2: begin
							price = 75;
						end
						3: begin
							price = 100;
						end				
					endcase
				end
				executou_start = 1;
			end			
			insert_money:begin
				if(!executou_insert_money) begin
					cdu = bin2bcd(dinheiro_inserido);
					dinheiro_inserido_c = cdu[11:8];
					dinheiro_inserido_d = cdu[7:4];
					dinheiro_inserido_u = cdu[3:0];
					moedas_carteira = moedas_carteira + moedas_inseridas;
				end
				executou_insert_money = 1;
			end
			give_change:begin
				if(!executou_give_change) begin
					if(dinheiro_inserido>=price) begin				
						valor_troco = dinheiro_inserido - price;
						if(valor_troco>0) moedas_troco = calcular_moedas_troco(valor_troco,moedas_carteira);
						else moedas_troco = moedas_inseridas;
						if(moedas_troco != 0) begin
							moedas_carteira = moedas_carteira - moedas_troco;
							carteira = carteira + price;
							produto_vendido = produto_escolhido;
						end
						else begin
							flag_sem_troco_devolver_dinheiro_inserido = 1;
							valor_troco = dinheiro_inserido;
							moedas_carteira = moedas_carteira - moedas_inseridas;
							moedas_troco = moedas_inseridas;
							produto_vendido = 0;
						end
					end
					else begin
						flag_dinheiro_insuficiente = 1;
						valor_troco = dinheiro_inserido;
						moedas_carteira = moedas_carteira - moedas_inseridas;
						moedas_troco = moedas_inseridas;
						produto_vendido = 0;
					end
				end
				executou_give_change = 1;
			end
			default:begin
	
			end
		endcase
		
	//o comando <= é uma atribuição não bloqueante.
	//significa que todos os lados direitos de todos os <= serão salvos ao entrar na função
	//de forma que se eu quisesse trocar os valores de x e y, poderia escrever
	//x<=y;y<=x
		
	//parte sequencial
	always @(posedge clock, negedge reset_n)
		if(~reset_n) begin 
			estado_atual<=espera;
		end
		//só entra na máquina de estados se
		//o reset_n for zero ao menos uma vez
		else begin
			case(estado_atual)
				espera:begin
					if(escolher) estado_atual <= start;
				end
				start:begin
					if(inserir_dinheiro && executou_start) estado_atual <= insert_money;
				end
				insert_money:begin
					if(dar_troco && executou_insert_money) estado_atual <= give_change;
				end
				give_change:begin
					if(escolher && executou_give_change) estado_atual <= espera;
				end
				default:begin
					estado_atual <= espera;
				end
			endcase
		end
		
	function automatic [23:0] calcular_moedas_troco;
		
		input [7:0] troco;
		input [23:0] moedascarteira;
		reg [23:0] moedas;
		reg [3:0] i,j,k;
		
		begin
			for (i = 0; i < moedascarteira[23:16]; i = i+1)
			begin
				for (j = 0; j < moedascarteira[15:8]; j = j+1)
				begin
					for (k = 0; k < moedascarteira[7:0]; k = k+1)
					begin
						if((25*k + 50*j + 100*i) == troco)
						begin
							moedas[7:0] = k;
						    moedas[15:8] = j;
						    moedas[23:16] = i;
							calcular_moedas_troco = moedas;
						end
					end
					k=0;
				end
				j=0;
			end
			calcular_moedas_troco = 0;
		end
	endfunction
		
	function automatic [11:0] bin2bcd;

		input [7:0] bin;
		reg [11:0] bcd; 
		reg [3:0] i;
		
		begin		
			//Double Dabble algorithm
			bcd = 0;
			for (i = 0; i < 8; i = i+1)
			begin
				bcd = {bcd[10:0],bin[7-i]}; //concatenation					
				//if a hex digit of 'bcd' is more than 4, add 3 to it.  
				if(i < 7 && bcd[3:0] > 4) 
					bcd[3:0] = bcd[3:0] + 3;
				if(i < 7 && bcd[7:4] > 4)
					bcd[7:4] = bcd[7:4] + 3;
				if(i < 7 && bcd[11:8] > 4)
					bcd[11:8] = bcd[11:8] + 3;  
			end
			bin2bcd = bcd;
		end
	endfunction

endmodule

source.v
module source(escolher, inserir_dinheiro, dar_troco, 
produto_escolhido, dinheiro_inserido, clock, reset_n,moedas_inseridas);

	input clock, reset_n;
	output reg[1:0] escolher, inserir_dinheiro, dar_troco;
	output reg[7:0] produto_escolhido, dinheiro_inserido;
	output reg[23:0] moedas_inseridas;
	
	initial begin 

	//primeira compra
	//dinheiro inserido = R$1,50
	//produto 1 = R$0,50
	//carteira = R$0,50
	//troco = R$1,00
	
	escolher=0;
	inserir_dinheiro=0;
	dar_troco=0;
	
	produto_escolhido = 0;
	dinheiro_inserido = 0;
	moedas_inseridas = 0;
	
	#10;
	
	escolher=1;
	inserir_dinheiro=0;
	dar_troco=0;
	
	produto_escolhido = 1;
	dinheiro_inserido = 0;
	
	#10;
	
	escolher=0;
	inserir_dinheiro=1;
	dar_troco=0;
	
	dinheiro_inserido = 150;
	moedas_inseridas[7:0] = 0; //0 moedas de R$0,25
	moedas_inseridas[15:8] = 1; //1 moeda de R$0,50
	moedas_inseridas[23:16] = 1; //1 moeda de R$1,00
	
	#10;
	
	escolher=0;
	inserir_dinheiro=0;
	dar_troco=1;
	
	#30;
	
	//segunda compra compra
	//dinheiro inserido = R$1,00
	//produto 2 = R$0,75
	//carteira = R$0,50 da primeira compra + R$0,75 dessa
	//carteira = R$1,25
	//troco = R$0,25
	
	escolher=0;
	inserir_dinheiro=0;
	dar_troco=0;
	
	produto_escolhido = 0;
	dinheiro_inserido = 0;
	moedas_inseridas = 0;
	
	#10;
	
	escolher=1;
	inserir_dinheiro=0;
	dar_troco=0;
	
	produto_escolhido = 2;
	dinheiro_inserido = 0;
	
	#10;
	
	escolher=0;
	inserir_dinheiro=1;
	dar_troco=0;
	
	dinheiro_inserido = 100;
	moedas_inseridas[7:0] = 2; //2 moedas de R$0,25
	moedas_inseridas[15:8] = 1; //1 moeda de R$0,50
	moedas_inseridas[23:16] = 0; //0 moeda de R$1,00
	
	#10;
	
	escolher=0;
	inserir_dinheiro=0;
	dar_troco=1;
	
	#10;

	end	
endmodule

main.v
`include "source.v"
`include "vm.v"

module main;

	reg clock,reset_n;
	wire[1:0]w_escolher,w_inserir_dinheiro,
		w_dar_troco;
	wire[7:0] w_produto_escolhido, 
		w_dinheiro_inserido,w_valor_troco,
		w_produto_vendido,w_carteira;
	wire[3:0] w_dinheiro_inserido_c, w_dinheiro_inserido_d, 
		w_dinheiro_inserido_u;
	wire[23:0] w_moedas_inseridas, w_moedas_carteira;
	
	source source(.escolher(w_escolher), 
				.inserir_dinheiro(w_inserir_dinheiro), 
				.dar_troco(w_dar_troco),
				.produto_escolhido(w_produto_escolhido),
				.dinheiro_inserido(w_dinheiro_inserido),
				.clock(clock),
				.reset_n(reset_n),
				.moedas_inseridas(w_moedas_inseridas));
				
	vm vm(.escolher(w_escolher), 
			.inserir_dinheiro(w_inserir_dinheiro), 
			.dar_troco(w_dar_troco), 							
			.produto_escolhido(w_produto_escolhido),
			.dinheiro_inserido(w_dinheiro_inserido),
			.produto_vendido(w_produto_vendido),
			.carteira(w_carteira),
			.valor_troco(w_valor_troco),
			.dinheiro_inserido_c(w_dinheiro_inserido_c),
			.dinheiro_inserido_d(w_dinheiro_inserido_d),
			.dinheiro_inserido_u(w_dinheiro_inserido_u),
			.reset_n(reset_n),
			.clock(clock),
			.moedas_inseridas(w_moedas_inseridas),
			.moedas_carteira(w_moedas_carteira));

	initial begin
		$dumpfile("vm.vcd");
		$dumpvars;

		clock = 0;
		reset_n= 0;
		#10
		reset_n = 1;
		#300 $finish;
	end
	always
		# 1 clock = ~clock;
		
endmodule

vm.vcd
$date
	Mon Jul 01 23:56:47 2019
$end
$version
	Icarus Verilog
$end
$timescale
	1s
$end
$scope module main $end
$var wire 8 ! w_valor_troco [7:0] $end
$var wire 8 " w_produto_vendido [7:0] $end
$var wire 8 # w_produto_escolhido [7:0] $end
$var wire 24 $ w_moedas_inseridas [23:0] $end
$var wire 24 % w_moedas_carteira [23:0] $end
$var wire 2 & w_inserir_dinheiro [1:0] $end
$var wire 2 ' w_escolher [1:0] $end
$var wire 4 ( w_dinheiro_inserido_u [3:0] $end
$var wire 4 ) w_dinheiro_inserido_d [3:0] $end
$var wire 4 * w_dinheiro_inserido_c [3:0] $end
$var wire 8 + w_dinheiro_inserido [7:0] $end
$var wire 2 , w_dar_troco [1:0] $end
$var wire 8 - w_carteira [7:0] $end
$var reg 1 . clock $end
$var reg 1 / reset_n $end
$scope module source $end
$var wire 1 . clock $end
$var wire 1 / reset_n $end
$var reg 2 0 dar_troco [1:0] $end
$var reg 8 1 dinheiro_inserido [7:0] $end
$var reg 2 2 escolher [1:0] $end
$var reg 2 3 inserir_dinheiro [1:0] $end
$var reg 24 4 moedas_inseridas [23:0] $end
$var reg 8 5 produto_escolhido [7:0] $end
$upscope $end
$scope module vm $end
$var wire 1 . clock $end
$var wire 2 6 dar_troco [1:0] $end
$var wire 8 7 dinheiro_inserido [7:0] $end
$var wire 2 8 escolher [1:0] $end
$var wire 2 9 inserir_dinheiro [1:0] $end
$var wire 24 : moedas_inseridas [23:0] $end
$var wire 8 ; produto_escolhido [7:0] $end
$var wire 1 / reset_n $end
$var reg 8 < carteira [7:0] $end
$var reg 12 = cdu [11:0] $end
$var reg 4 > dinheiro_inserido_c [3:0] $end
$var reg 4 ? dinheiro_inserido_d [3:0] $end
$var reg 4 @ dinheiro_inserido_u [3:0] $end
$var reg 2 A estado_atual [1:0] $end
$var reg 2 B executou_give_change [1:0] $end
$var reg 2 C executou_insert_money [1:0] $end
$var reg 2 D executou_start [1:0] $end
$var reg 2 E flag_dinheiro_insuficiente [1:0] $end
$var reg 2 F flag_sem_troco_devolver_dinheiro_inserido [1:0] $end
$var reg 24 G moedas_carteira [23:0] $end
$var reg 24 H moedas_troco [23:0] $end
$var reg 8 I price [7:0] $end
$var reg 8 J produto_vendido [7:0] $end
$var reg 8 K valor_troco [7:0] $end
$scope function bin2bcd $end
$upscope $end
$scope function calcular_moedas_troco $end
$upscope $end
$upscope $end
$upscope $end
$enddefinitions $end
#0
$dumpvars
b0 K
b0 J
b0 I
b0 H
b0 G
b0 F
b0 E
b0 D
b0 C
b0 B
b0 A
b0 @
b0 ?
b0 >
b0 =
b0 <
b0 ;
b0 :
b0 9
b0 8
b0 7
b0 6
b0 5
b0 4
b0 3
b0 2
b0 1
b0 0
0/
0.
b0 -
b0 ,
b0 +
b0 *
b0 )
b0 (
b0 '
b0 &
b0 %
b0 $
b0 #
b0 "
b0 !
$end
#1
1.
#2
0.
#3
1.
#4
0.
#5
1.
#6
0.
#7
1.
#8
0.
#9
1.
#10
0.
1/
b1 #
b1 5
b1 ;
b1 '
b1 2
b1 8
#11
b1 A
1.
#12
0.
#13
b1 D
b110010 I
1.
#14
0.
#15
1.
#16
0.
#17
1.
#18
0.
#19
1.
#20
0.
b10000000100000000 $
b10000000100000000 4
b10000000100000000 :
b10010110 +
b10010110 1
b10010110 7
b1 &
b1 3
b1 9
b0 '
b0 2
b0 8
#21
b10 A
1.
#22
0.
#23
b1 C
b10000000100000000 %
b10000000100000000 G
b101 )
b101 ?
b1 *
b1 >
b101010000 =
1.
#24
0.
#25
1.
#26
0.
#27
1.
#28
0.
#29
1.
#30
0.
b1 ,
b1 0
b1 6
b0 &
b0 3
b0 9
#31
b11 A
1.
#32
0.
#33
b1 B
b10000000100000000 H
b0 %
b0 G
b1 F
b10010110 !
b10010110 K
1.
#34
0.
#35
1.
#36
0.
#37
1.
#38
0.
#39
1.
#40
0.
#41
1.
#42
0.
#43
1.
#44
0.
#45
1.
#46
0.
#47
1.
#48
0.
#49
1.
#50
0.
#51
1.
#52
0.
#53
1.
#54
0.
#55
1.
#56
0.
#57
1.
#58
0.
#59
1.
#60
0.
b0 $
b0 4
b0 :
b0 +
b0 1
b0 7
b0 #
b0 5
b0 ;
b0 ,
b0 0
b0 6
#61
1.
#62
0.
#63
1.
#64
0.
#65
1.
#66
0.
#67
1.
#68
0.
#69
1.
#70
0.
b10 #
b10 5
b10 ;
b1 '
b1 2
b1 8
#71
b0 A
1.
#72
0.
#73
b1 A
b0 B
b0 C
b0 D
b0 =
b0 H
b0 )
b0 ?
b0 *
b0 >
b0 !
b0 K
b0 I
b0 F
1.
#74
0.
#75
b1 D
b1001011 I
1.
#76
0.
#77
1.
#78
0.
#79
1.
#80
0.
b100000010 $
b100000010 4
b100000010 :
b1100100 +
b1100100 1
b1100100 7
b1 &
b1 3
b1 9
b0 '
b0 2
b0 8
#81
b10 A
1.
#82
0.
#83
b1 C
b100000010 %
b100000010 G
b1 *
b1 >
b100000000 =
1.
#84
0.
#85
1.
#86
0.
#87
1.
#88
0.
#89
1.
#90
0.
b1 ,
b1 0
b1 6
b0 &
b0 3
b0 9
#91
b11 A
1.
#92
0.
#93
b1 B
b100000010 H
b0 %
b0 G
b1 F
b1100100 !
b1100100 K
1.
