vm.v
module vm(escolher,inserir_dinheiro,dar_troco,
produto_escolhido, dinheiro_inserido, produto_vendido,
carteira,valor_troco,dinheiro_inserido_c, dinheiro_inserido_d,
dinheiro_inserido_u, reset_n,clock);

	input escolher, inserir_dinheiro, dar_troco;
	input[7:0] produto_escolhido, dinheiro_inserido;
	input reset_n;
	input clock;
	output reg[7:0] produto_vendido, carteira, valor_troco;
	output reg[3:0]	dinheiro_inserido_c, dinheiro_inserido_d, dinheiro_inserido_u;
	
	input[11:0] moedas_inseridas;
	output reg[11:0] moedas_carteira; //11 bits -> R$1,00[11:8] R$0,50[7:4] R$0,25[3:0]
	
	reg[1:0] estado_atual;
	reg[7:0] price;
	reg[11:0] cdu;
	
	parameter espera=0,start=1,insert_money=2,give_change=3;
	
	//parte combinacional
	always @(posedge clock, negedge reset_n)
		if(~reset_n) begin 
			price = 0;
			carteira = 0;
			valor_troco = 0;
			dinheiro_inserido_c = 0;
			dinheiro_inserido_d = 0;
			dinheiro_inserido_u = 0;
			produto_vendido = 0;
			cdu=0;
		end
		else
		case(estado_atual)
			espera:begin
				//carteira não é zerada
				price = 0;
				valor_troco = 0;
				dinheiro_inserido_c = 0;
				dinheiro_inserido_d = 0;
				dinheiro_inserido_u = 0;
				produto_vendido = 0;
				cdu=0;			
			end
			start:begin
				case(produto_escolhido)
					1: begin
						price = 50;
					end
					2: begin
						price = 75;
					end
					3: begin
						price = 100;
					end				
				endcase							
			end			
			insert_money:begin
				cdu = bin2bcd(dinheiro_inserido);
				dinheiro_inserido_c = cdu[11:8];
				dinheiro_inserido_d = cdu[7:4];
				dinheiro_inserido_u = cdu[3:0];
			end
			give_change:begin
				if(dinheiro_inserido>price)
				begin
					valor_troco = dinheiro_inserido - price;
					carteira = price;
					produto_vendido = escolher;
				end
			end
			default:begin

			end
		endcase
		
	//o comando <= é uma atribuição não bloqueante.
	//significa que todos os lados direitos de todos os <= serão salvos ao entrar na função
	//de forma que se eu quisesse trocar os valores de x e y, poderia escrever
	//x<=y;y<=x
		
	//parte sequencial
	always @(posedge clock, negedge reset_n)
		if(~reset_n) begin 
			estado_atual<=espera;
		end
		//só entra na máquina de estados se
		//o reset_n for zero ao menos uma vez
		else case(estado_atual)
			espera:begin
				if(escolher) estado_atual <= start;
			end
			start:begin
				if(inserir_dinheiro) estado_atual <= insert_money;
			end
			insert_money:begin
				if(dar_troco & (dinheiro_inserido >= price)) 
				estado_atual <= give_change;
			end
			give_change:begin
				if(escolher) estado_atual <= start;
			end
			default:begin
				estado_atual <= espera;
			end
		endcase
		
	function automatic [11:0] bin2bcd;

		input [7:0] bin;
		reg [11:0] bcd; 
		reg [3:0] i;
		
		begin		
			//Double Dabble algorithm
			bcd = 0;
			for (i = 0; i < 8; i = i+1)
				begin
					bcd = {bcd[10:0],bin[7-i]}; //concatenation
						
					//if a hex digit of 'bcd' is more than 4, add 3 to it.  
					if(i < 7 && bcd[3:0] > 4) 
						bcd[3:0] = bcd[3:0] + 3;
					if(i < 7 && bcd[7:4] > 4)
						bcd[7:4] = bcd[7:4] + 3;
					if(i < 7 && bcd[11:8] > 4)
						bcd[11:8] = bcd[11:8] + 3;  
				end
			bin2bcd = bcd;
		end
	endfunction

endmodule

source.v
module source(escolher, inserir_dinheiro, dar_troco, 
produto_escolhido, dinheiro_inserido, clock, reset_n);

	input clock, reset_n;
	output reg escolher, inserir_dinheiro, dar_troco;
	output reg[7:0] produto_escolhido, dinheiro_inserido;
	
	initial begin 

	//primeira compra
	//dinheiro inserido = R$1,50
	//produto 1 = R$0,50
	//carteira = R$0,50
	//troco = R$1,00
	
	escolher=0;
	inserir_dinheiro=0;
	dar_troco=0;
	
	produto_escolhido = 0;
	dinheiro_inserido = 0;
	
	#10;
	
	escolher=1;
	inserir_dinheiro=0;
	dar_troco=0;
	
	produto_escolhido = 1;
	dinheiro_inserido = 0;
	
	#10;
	
	escolher=0;
	inserir_dinheiro=1;
	dar_troco=0;
	
	dinheiro_inserido = 150;
	
	#10;
	
	escolher=0;
	inserir_dinheiro=0;
	dar_troco=1;
	
	#10;
	
	//segunda compra compra
	//dinheiro inserido = R$1,00
	//produto 2 = R$0,75
	//carteira = R$0,50 da primeira compra + R$0,75 dessa
	//carteira = R$1,25
	//troco = R$0,25
	
	escolher=0;
	inserir_dinheiro=0;
	dar_troco=0;
	
	produto_escolhido = 0;
	dinheiro_inserido = 0;
	
	#10;
	
	escolher=1;
	inserir_dinheiro=0;
	dar_troco=0;
	
	produto_escolhido = 2;
	dinheiro_inserido = 0;
	
	#10;
	
	escolher=0;
	inserir_dinheiro=1;
	dar_troco=0;
	
	dinheiro_inserido = 100;
	
	#10;
	
	escolher=0;
	inserir_dinheiro=0;
	dar_troco=1;
	
	#10;

	end	
endmodule

main.v
`include "source.v"
`include "vm.v"

module main;

	reg clock,reset_n;
	wire w_escolher,w_inserir_dinheiro,
		w_dar_troco;
	wire[7:0] w_produto_escolhido, 
		w_dinheiro_inserido,w_valor_troco,
		w_produto_vendido,w_carteira;
	wire[3:0] w_dinheiro_inserido_c, w_dinheiro_inserido_d, 
		w_dinheiro_inserido_u;
	
	source source(.escolher(w_escolher), 
				.inserir_dinheiro(w_inserir_dinheiro), 
				.dar_troco(w_dar_troco),
				.produto_escolhido(w_produto_escolhido),
				.dinheiro_inserido(w_dinheiro_inserido),
				.clock(clock),
				.reset_n(reset_n));
				
	vm vm(.escolher(w_escolher), 
			.inserir_dinheiro(w_inserir_dinheiro), 
			.dar_troco(w_dar_troco), 							
			.produto_escolhido(w_produto_escolhido),
			.dinheiro_inserido(w_dinheiro_inserido),
			.produto_vendido(w_produto_vendido),
			.carteira(w_carteira),
			.valor_troco(w_valor_troco),
			.dinheiro_inserido_c(w_dinheiro_inserido_c),
			.dinheiro_inserido_d(w_dinheiro_inserido_d),
			.dinheiro_inserido_u(w_dinheiro_inserido_u),
			.reset_n(reset_n),
			.clock(clock));

	initial begin
		$dumpfile("vm.vcd");
		$dumpvars;

		clock = 0;
		reset_n= 0;
		#10
		reset_n = 1;
		#300 $finish;
	end
	always
		# 1 clock = ~clock;
		
endmodule

vm.vcd
$date
	Mon Jul 01 21:09:28 2019
$end
$version
	Icarus Verilog
$end
$timescale
	1s
$end
$scope module main $end
$var wire 8 ! w_valor_troco [7:0] $end
$var wire 8 " w_produto_vendido [7:0] $end
$var wire 8 # w_produto_escolhido [7:0] $end
$var wire 1 $ w_inserir_dinheiro $end
$var wire 1 % w_escolher $end
$var wire 4 & w_dinheiro_inserido_u [3:0] $end
$var wire 4 ' w_dinheiro_inserido_d [3:0] $end
$var wire 4 ( w_dinheiro_inserido_c [3:0] $end
$var wire 8 ) w_dinheiro_inserido [7:0] $end
$var wire 1 * w_dar_troco $end
$var wire 8 + w_carteira [7:0] $end
$var reg 1 , clock $end
$var reg 1 - reset_n $end
$scope module source $end
$var wire 1 , clock $end
$var wire 1 - reset_n $end
$var reg 1 * dar_troco $end
$var reg 8 . dinheiro_inserido [7:0] $end
$var reg 1 % escolher $end
$var reg 1 $ inserir_dinheiro $end
$var reg 8 / produto_escolhido [7:0] $end
$upscope $end
$scope module vm $end
$var wire 1 , clock $end
$var wire 1 * dar_troco $end
$var wire 8 0 dinheiro_inserido [7:0] $end
$var wire 1 % escolher $end
$var wire 1 $ inserir_dinheiro $end
$var wire 8 1 produto_escolhido [7:0] $end
$var wire 1 - reset_n $end
$var reg 8 2 carteira [7:0] $end
$var reg 12 3 cdu [11:0] $end
$var reg 4 4 dinheiro_inserido_c [3:0] $end
$var reg 4 5 dinheiro_inserido_d [3:0] $end
$var reg 4 6 dinheiro_inserido_u [3:0] $end
$var reg 2 7 estado_atual [1:0] $end
$var reg 8 8 price [7:0] $end
$var reg 8 9 produto_vendido [7:0] $end
$var reg 8 : valor_troco [7:0] $end
$scope function bin2bcd $end
$upscope $end
$upscope $end
$upscope $end
$enddefinitions $end
#0
$dumpvars
b0 :
b0 9
b0 8
b0 7
b0 6
b0 5
b0 4
b0 3
b0 2
b0 1
b0 0
b0 /
b0 .
0-
0,
b0 +
0*
b0 )
b0 (
b0 '
b0 &
0%
0$
b0 #
b0 "
b0 !
$end
#1
1,
#2
0,
#3
1,
#4
0,
#5
1,
#6
0,
#7
1,
#8
0,
#9
1,
#10
0,
1-
b1 #
b1 /
b1 1
1%
#11
b1 7
1,
#12
0,
#13
b110010 8
1,
#14
0,
#15
1,
#16
0,
#17
1,
#18
0,
#19
1,
#20
0,
b10010110 )
b10010110 .
b10010110 0
1$
0%
#21
b10 7
1,
#22
0,
#23
b101 '
b101 5
b1 (
b1 4
b101010000 3
1,
#24
0,
#25
1,
#26
0,
#27
1,
#28
0,
#29
1,
#30
0,
1*
0$
#31
b11 7
1,
#32
0,
#33
b110010 +
b110010 2
b1100100 !
b1100100 :
1,
#34
0,
#35
1,
#36
0,
#37
1,
#38
0,
#39
1,
#40
0,
b0 )
b0 .
b0 0
b0 #
b0 /
b0 1
0*
#41
1,
#42
0,
#43
1,
#44
0,
#45
1,
#46
0,
#47
1,
#48
0,
#49
1,
#50
0,
b10 #
b10 /
b10 1
1%
#51
b1 7
1,
#52
0,
#53
b1001011 8
1,
#54
0,
#55
1,
#56
0,
#57
1,
#58
0,
#59
1,
#60
0,
b1100100 )
b1100100 .
b1100100 0
1$
0%
#61
b10 7
1,
#62
0,
#63
b0 '
b0 5
b100000000 3
1,
#64
0,
#65
1,
#66
0,
#67
1,
#68
0,
#69
1,
#70
0,
1*
0$
#71
b11 7
1,
#72
0,
#73
b1001011 +
b1001011 2
b11001 !
b11001 :
1,
